fnexpr/__init__.py
fnexpr/vars.py
fnexpr-0.1.dist-info/LICENSE
fnexpr-0.1.dist-info/WHEEL
fnexpr-0.1.dist-info/METADATA
fnexpr-0.1.dist-info/RECORD
